brightdata/__init__.py
brightdata/auto.py
brightdata/models.py
brightdata/web_unlocker.py
brightdata/browserapi/__init__.py
brightdata/browserapi/browser_api.py
brightdata/browserapi/browser_config.py
brightdata/browserapi/browser_pool.py
brightdata/browserapi/browserapi_engine.py
brightdata/browserapi/playwright_session.py
brightdata/browserapi/browser_api_variants/__init__.py
brightdata/browserapi/browser_api_variants/check_max_concurrency_ceiling.py
brightdata/browserapi/browser_api_variants/isolated_playwright_session.py
brightdata/browserapi/browser_api_variants/new_browser_api.py
brightdata/browserapi/browser_api_variants/old2_new_browser_api.py
brightdata/browserapi/browser_api_variants/old_new_browser_api.py
brightdata/browserapi/browser_api_variants/old_stress_test_browser_api.py
brightdata/browserapi/browser_api_variants/pool.py
brightdata/browserapi/browser_api_variants/semaphore.py
brightdata/browserapi/browser_api_variants/stress_test_browser_api.py
brightdata/crawlerapi/__init__.py
brightdata/crawlerapi/crawler_api.py
brightdata/utils/__init__.py
brightdata/utils/utils.py
brightdata/webscraper_api/__init__.py
brightdata/webscraper_api/base_specialized_scraper.py
brightdata/webscraper_api/engine.py
brightdata/webscraper_api/registry.py
brightdata/webscraper_api/scrapers/__init__.py
brightdata/webscraper_api/scrapers/amazon/__init__.py
brightdata/webscraper_api/scrapers/amazon/async_tests.py
brightdata/webscraper_api/scrapers/amazon/scraper.py
brightdata/webscraper_api/scrapers/amazon/tests.py
brightdata/webscraper_api/scrapers/digikey/__init__.py
brightdata/webscraper_api/scrapers/digikey/scraper.py
brightdata/webscraper_api/scrapers/digikey/tests.py
brightdata/webscraper_api/scrapers/instagram/__init__.py
brightdata/webscraper_api/scrapers/instagram/scraper.py
brightdata/webscraper_api/scrapers/instagram/tests.py
brightdata/webscraper_api/scrapers/linkedin/__init__.py
brightdata/webscraper_api/scrapers/linkedin/scraper.py
brightdata-0.4.0.3.dist-info/METADATA
brightdata-0.4.0.3.dist-info/WHEEL
brightdata-0.4.0.3.dist-info/top_level.txt
brightdata-0.4.0.3.dist-info/RECORD
