Metadata-Version: 2.4
Name: brightdata
Version: 0.4.0.3
Summary: Easy to use comprehensive wrapper for brightdata *scrapers, web unlocker, browserapi APIs with async support
Author: Enes Kuzucu
Classifier: Development Status :: 3 - Alpha
Classifier: Intended Audience :: Developers
Classifier: License :: OSI Approved :: MIT License
Classifier: Programming Language :: Python :: 3
Classifier: Programming Language :: Python :: 3.7
Classifier: Programming Language :: Python :: 3.8
Classifier: Programming Language :: Python :: 3.9
Classifier: Programming Language :: Python :: 3.10
Classifier: Operating System :: OS Independent
Requires-Python: >=3.7
Requires-Dist: python-dotenv
Requires-Dist: requests
Requires-Dist: aiohttp
Requires-Dist: tldextract
Requires-Dist: pyyaml
Requires-Dist: tldextract
Requires-Dist: selenium
Requires-Dist: playwright
Dynamic: author
Dynamic: classifier
Dynamic: description
Dynamic: description-content-type
Dynamic: requires-dist
Dynamic: requires-python
Dynamic: summary
